flask_rollup/__init__.py
flask_rollup/cli.py
Flask_Rollup-0.3.1.dist-info/LICENSE
Flask_Rollup-0.3.1.dist-info/METADATA
Flask_Rollup-0.3.1.dist-info/WHEEL
Flask_Rollup-0.3.1.dist-info/entry_points.txt
Flask_Rollup-0.3.1.dist-info/top_level.txt
Flask_Rollup-0.3.1.dist-info/RECORD
