Metadata-Version: 2.1
Name: Flask-Rollup
Version: 0.3.1
Summary: Rollup integration with Flask web framework
Home-page: https://github.com/zgoda/flask-rollup
Author: Jarek Zgoda
License: BSD-3-Clause
Project-URL: Documentation, https://flask-rollup.readthedocs.io/
Project-URL: Source, https://github.com/zgoda/flask-rollup
Project-URL: Issues, https://github.com/zgoda/flask-rollup/issues
Classifier: Development Status :: 4 - Beta
Classifier: Environment :: Plugins
Classifier: Environment :: Web Environment
Classifier: Framework :: Flask
Classifier: Intended Audience :: Developers
Classifier: License :: OSI Approved :: BSD License
Classifier: Operating System :: OS Independent
Classifier: Programming Language :: JavaScript
Classifier: Programming Language :: Python :: 3 :: Only
Classifier: Programming Language :: Python :: 3.8
Classifier: Programming Language :: Python :: 3.9
Classifier: Programming Language :: Python :: 3.10
Classifier: Topic :: Internet :: WWW/HTTP :: Dynamic Content
Classifier: Topic :: Software Development :: Build Tools
Requires-Python: ~=3.8
License-File: LICENSE
Requires-Dist: Flask (<2.3,>=1.1)
Provides-Extra: dev
Requires-Dist: ipdb ; extra == 'dev'
Requires-Dist: flake8 ; extra == 'dev'
Requires-Dist: flake8-builtins ; extra == 'dev'
Requires-Dist: flake8-bugbear ; extra == 'dev'
Requires-Dist: flake8-comprehensions ; extra == 'dev'
Requires-Dist: pep8-naming ; extra == 'dev'
Requires-Dist: dlint ; extra == 'dev'
Requires-Dist: rstcheck ; extra == 'dev'
Requires-Dist: rope ; extra == 'dev'
Requires-Dist: isort ; extra == 'dev'
Requires-Dist: wheel ; extra == 'dev'
Requires-Dist: flask-shell-ipython ; extra == 'dev'
Requires-Dist: watchdog ; extra == 'dev'
Requires-Dist: pytest ; extra == 'dev'
Requires-Dist: pytest-cov ; extra == 'dev'
Requires-Dist: pytest-mock ; extra == 'dev'
Requires-Dist: Sphinx ; extra == 'dev'
Provides-Extra: docs
Requires-Dist: Sphinx ; extra == 'docs'
Provides-Extra: test
Requires-Dist: pytest ; extra == 'test'
Requires-Dist: pytest-cov ; extra == 'test'
Requires-Dist: pytest-mock ; extra == 'test'
